untidy/__init__.py
untidy/contaminators.py
untidy/main.py
untidy-0.0.1a4.dist-info/LICENSE
untidy-0.0.1a4.dist-info/METADATA
untidy-0.0.1a4.dist-info/WHEEL
untidy-0.0.1a4.dist-info/top_level.txt
untidy-0.0.1a4.dist-info/RECORD
