Metadata-Version: 2.1
Name: untidy
Version: 0.0.1a4
Summary: Python package for creating messy data.
Home-page: https://github.com/dainstudios/untidy
Author: Paolo Fantinel, Sinem Unal Nazaroglu, Mate Varadi
Author-email: paolo.fantinel@dainstudios.com, sinem.nazaroglu@dainstudios.com, mate.varadi@dainstudios.com
License: MIT
Platform: UNKNOWN
Classifier: Programming Language :: Python :: 3.8
Classifier: Programming Language :: Python :: 3.9
Classifier: License :: OSI Approved :: MIT License
Classifier: Operating System :: OS Independent
Requires-Python: >=3.8
License-File: LICENSE
Requires-Dist: numpy (>=1.10.4)
Requires-Dist: pandas (>=0.17.1)
Provides-Extra: dev
Requires-Dist: pytest (>=6.2.0) ; extra == 'dev'
Provides-Extra: examples
Requires-Dist: jupyter ; extra == 'examples'
Requires-Dist: seaborn (>=0.7.0) ; extra == 'examples'
